[
  {
    "id": 1,
    "title": "Академия Платона",
    "durationYears": 40,
    "isActive": false,
    "foundingDate": "-387-01-01",
    "philosophers": [
      "Платон",
      "Аристотель",
      "Ксенократ",
      "Спевсипп"
    ]
  },
  {
    "id": 2,
    "title": "Лицей Аристотеля",
    "durationYears": 35,
    "isActive": false,
    "foundingDate": "-335-01-01",
    "philosophers": [
      "Аристотель",
      "Теофраст",
      "Аристоксен",
      "Дикеарх"
    ]
  },
  {
    "id": 52,
    "title": "Стоицизм",
    "durationYears": 500,
    "isActive": false,
    "foundingDate": "-300-01-01",
    "philosophers": [
      "Зенон Китийский",
      "Сенека",
      "Эпиктет",
      "Марк Аврелий"
    ]
  }
]